bitbucket/__init__.py
bitbucket/exceptions.py
bitbucket/resource.py
bitbucket/tool.py
bitbucketpy-0.1.12.dist-info/LICENSE
bitbucketpy-0.1.12.dist-info/METADATA
bitbucketpy-0.1.12.dist-info/WHEEL
bitbucketpy-0.1.12.dist-info/top_level.txt
bitbucketpy-0.1.12.dist-info/RECORD
