Metadata-Version: 2.1
Name: bitbucketpy
Version: 0.1.12
Summary: Simple library for interacting with the Bitbucket Cloud API
Home-page: https://github.com/sarvin/bitbucketpy
Author: Sarvin Coachbuilder
Author-email: sarvinc@gmail.com
License: UNKNOWN
Project-URL: Bug Tracker, https://github.com/sarvin/bitbucketpy/issues
Keywords: Bitbucket
Platform: UNKNOWN
Classifier: Programming Language :: Python :: 3
Classifier: Programming Language :: Python :: 3.6
Classifier: Programming Language :: Python :: 3.7
Classifier: Programming Language :: Python :: 3.8
Classifier: Programming Language :: Python :: 3.9
Classifier: License :: OSI Approved :: GNU General Public License v3 (GPLv3)
Classifier: Operating System :: OS Independent
Classifier: Development Status :: 3 - Alpha
Classifier: Natural Language :: English
Requires-Python: >=3.6
License-File: LICENSE
Requires-Dist: requests
Provides-Extra: develop
Requires-Dist: ipython ; extra == 'develop'
Provides-Extra: test
Requires-Dist: vcrpy (==4.1.1) ; extra == 'test'
